nonebot_plugin_yoyogame/__init__.py
nonebot_plugin_yoyogame/config.py
nonebot_plugin_yoyogame/yoyoutils.py
nonebot_plugin_yoyogame-0.2.1.dist-info/LICENSE
nonebot_plugin_yoyogame-0.2.1.dist-info/METADATA
nonebot_plugin_yoyogame-0.2.1.dist-info/WHEEL
nonebot_plugin_yoyogame-0.2.1.dist-info/top_level.txt
nonebot_plugin_yoyogame-0.2.1.dist-info/RECORD
