Metadata-Version: 2.1
Name: nonebot-plugin-yoyogame
Version: 0.2.1
Summary: 一个基于Nonebot开发的悠悠小游戏
Author-email: ChenXu233 <Woyerpa@outlook.com>
License: GPL
Requires-Python: >=3.10
License-File: LICENSE
Requires-Dist: pandas>=2.2.2
Requires-Dist: terminaltables>=3.1.10
Requires-Dist: nonebot2>=2.3.3
Requires-Dist: nonebot-adapter-onebot>=2.4.4
Requires-Dist: nonebot-plugin-alconna>=0.52.1
Requires-Dist: nonebot-plugin-cesaa>=0.4.0
Requires-Dist: nonebot-plugin-session>=0.3.2
